restic_qdirstat/__init__.py
restic_qdirstat/lib.py
restic_qdirstat-0.1.0.dist-info/licenses/LICENSE
restic_qdirstat-0.1.0.dist-info/METADATA
restic_qdirstat-0.1.0.dist-info/WHEEL
restic_qdirstat-0.1.0.dist-info/entry_points.txt
restic_qdirstat-0.1.0.dist-info/top_level.txt
restic_qdirstat-0.1.0.dist-info/RECORD
