Metadata-Version: 2.4
Name: restic-qdirstat
Version: 0.1.0
Summary: Analyze restic snapshots with QDirStat
Requires-Python: >=3.12
License-File: LICENSE
Dynamic: license-file
